{"status":"done","chunks":{"main":[{"name":"main.js","path":"C:\\Users\\vlexh\\cride\\cride\\frontend\\static\\bundles\\main.js"}]},"error":"ModuleBuildError","message":"Module build failed (from ./node_modules/babel-loader/lib/index.js):\nSyntaxError: C:\\Users\\vlexh\\cride\\cride\\frontend\\src\\components\\Layout\\Header.jsx: Unexpected token, expected \",\" (21:37)\n\n  19 |     let location = useLocation();\n  20 |     useEffect(() => {\n> 21 |         console.log(location.pathname.0.match(/\\/teachers/))\n     |                                      ^\n  22 | \n  23 |     })\n  24 |     const [send, setSend] = useState(false);\n    at Object._raise (C:\\Users\\vlexh\\cride\\node_modules\\@babel\\parser\\lib\\index.js:742:17)\n    at Object.raiseWithData (C:\\Users\\vlexh\\cride\\node_modules\\@babel\\parser\\lib\\index.js:735:17)\n    at Object.raise (C:\\Users\\vlexh\\cride\\node_modules\\@babel\\parser\\lib\\index.js:729:17)\n    at Object.unexpected (C:\\Users\\vlexh\\cride\\node_modules\\@babel\\parser\\lib\\index.js:8757:16)\n    at Object.expect (C:\\Users\\vlexh\\cride\\node_modules\\@babel\\parser\\lib\\index.js:8743:28)\n    at Object.parseCallExpressionArguments (C:\\Users\\vlexh\\cride\\node_modules\\@babel\\parser\\lib\\index.js:9770:14)\n    at Object.parseSubscript (C:\\Users\\vlexh\\cride\\node_modules\\@babel\\parser\\lib\\index.js:9696:31)\n    at Object.parseSubscripts (C:\\Users\\vlexh\\cride\\node_modules\\@babel\\parser\\lib\\index.js:9625:19)\n    at Object.parseExprSubscripts (C:\\Users\\vlexh\\cride\\node_modules\\@babel\\parser\\lib\\index.js:9608:17)\n    at Object.parseMaybeUnary (C:\\Users\\vlexh\\cride\\node_modules\\@babel\\parser\\lib\\index.js:9582:21)\n    at Object.parseExprOps (C:\\Users\\vlexh\\cride\\node_modules\\@babel\\parser\\lib\\index.js:9452:23)\n    at Object.parseMaybeConditional (C:\\Users\\vlexh\\cride\\node_modules\\@babel\\parser\\lib\\index.js:9425:23)\n    at Object.parseMaybeAssign (C:\\Users\\vlexh\\cride\\node_modules\\@babel\\parser\\lib\\index.js:9380:21)\n    at Object.parseExpression (C:\\Users\\vlexh\\cride\\node_modules\\@babel\\parser\\lib\\index.js:9332:23)\n    at Object.parseStatementContent (C:\\Users\\vlexh\\cride\\node_modules\\@babel\\parser\\lib\\index.js:11210:23)\n    at Object.parseStatement (C:\\Users\\vlexh\\cride\\node_modules\\@babel\\parser\\lib\\index.js:11081:17)\n    at Object.parseBlockOrModuleBlockBody (C:\\Users\\vlexh\\cride\\node_modules\\@babel\\parser\\lib\\index.js:11656:25)\n    at Object.parseBlockBody (C:\\Users\\vlexh\\cride\\node_modules\\@babel\\parser\\lib\\index.js:11642:10)\n    at Object.parseBlock (C:\\Users\\vlexh\\cride\\node_modules\\@babel\\parser\\lib\\index.js:11626:10)\n    at Object.parseFunctionBody (C:\\Users\\vlexh\\cride\\node_modules\\@babel\\parser\\lib\\index.js:10634:24)\n    at Object.parseArrowExpression (C:\\Users\\vlexh\\cride\\node_modules\\@babel\\parser\\lib\\index.js:10603:10)\n    at Object.parseParenAndDistinguishExpression (C:\\Users\\vlexh\\cride\\node_modules\\@babel\\parser\\lib\\index.js:10221:12)\n    at Object.parseExprAtom (C:\\Users\\vlexh\\cride\\node_modules\\@babel\\parser\\lib\\index.js:9947:21)\n    at Object.parseExprAtom (C:\\Users\\vlexh\\cride\\node_modules\\@babel\\parser\\lib\\index.js:4614:20)\n    at Object.parseExprSubscripts (C:\\Users\\vlexh\\cride\\node_modules\\@babel\\parser\\lib\\index.js:9602:23)\n    at Object.parseMaybeUnary (C:\\Users\\vlexh\\cride\\node_modules\\@babel\\parser\\lib\\index.js:9582:21)\n    at Object.parseExprOps (C:\\Users\\vlexh\\cride\\node_modules\\@babel\\parser\\lib\\index.js:9452:23)\n    at Object.parseMaybeConditional (C:\\Users\\vlexh\\cride\\node_modules\\@babel\\parser\\lib\\index.js:9425:23)\n    at Object.parseMaybeAssign (C:\\Users\\vlexh\\cride\\node_modules\\@babel\\parser\\lib\\index.js:9380:21)\n    at Object.parseExprListItem (C:\\Users\\vlexh\\cride\\node_modules\\@babel\\parser\\lib\\index.js:10718:18)"}